SlyTwitter/__init__.py
SlyTwitter/__main__.py
SlyTwitter/common.py
SlyTwitter/twitter.py
SlyTwitter/twitter_upload.py
SlyTwitter/twitter_v2.py
SlyTwitter-0.2.0.dist-info/LICENSE
SlyTwitter-0.2.0.dist-info/METADATA
SlyTwitter-0.2.0.dist-info/WHEEL
SlyTwitter-0.2.0.dist-info/top_level.txt
SlyTwitter-0.2.0.dist-info/RECORD
